duco/__init__.py
duco/command_line.py
duco/const.py
duco/duco.py
duco/enum_types.py
duco/modbus.py
duco/nodes.py
python_duco-0.1.0.dist-info/DESCRIPTION.rst
python_duco-0.1.0.dist-info/METADATA
python_duco-0.1.0.dist-info/RECORD
python_duco-0.1.0.dist-info/WHEEL
python_duco-0.1.0.dist-info/entry_points.txt
python_duco-0.1.0.dist-info/metadata.json
python_duco-0.1.0.dist-info/top_level.txt
